<?xml version="1.0" encoding="UTF-8"?>
<MF0 version="1.1" packageUris="http://schema.mathworks.com/mf0/sl_modelref_info/R2018b">
  <ModelRefInfoRepo.ModelRefInfoRoot type="ModelRefInfoRepo.ModelRefInfoRoot" uuid="b036ad14-55a8-4000-b9b1-e1d92891ce80">
    <autoSolverStatusFlags>327</autoSolverStatusFlags>
    <childModelRefInfo type="ModelRefInfoRepo.ChildModelRefInfo" uuid="72c4fe93-6fe2-43c8-a35e-95faf287c652">
      <modelName>Subsystem</modelName>
      <modelPath>Subsystem</modelPath>
    </childModelRefInfo>
    <dataTransferInfos>AAFJTQAAAAAOAAAAOAAAAAYAAAAIAAAAAgAAAAAAAAAFAAAACAAAAAAAAAABAAAAAQAAAAAAAAAFAAQAAQAAAAEAAAAAAAAA</dataTransferInfos>
    <defaultsCMapping>{&quot;Inports&quot;:&quot;{\&quot;Name\&quot;:\&quot;Default\&quot;,\&quot;Checksum\&quot;:\&quot;Default\&quot;,\&quot;PerInstancePropertiesChecksum\&quot;:\&quot;\&quot;,\&quot;MemorySectionName\&quot;:\&quot;None\&quot;,\&quot;MemorySectionChecksum\&quot;:\&quot;None\&quot;}&quot;,&quot;Outports&quot;:&quot;{\&quot;Name\&quot;:\&quot;Default\&quot;,\&quot;Checksum\&quot;:\&quot;Default\&quot;,\&quot;PerInstancePropertiesChecksum\&quot;:\&quot;\&quot;,\&quot;MemorySectionName\&quot;:\&quot;None\&quot;,\&quot;MemorySectionChecksum\&quot;:\&quot;None\&quot;}&quot;,&quot;GlobalParameters&quot;:&quot;{\&quot;Name\&quot;:\&quot;Default\&quot;,\&quot;Checksum\&quot;:\&quot;Default\&quot;,\&quot;PerInstancePropertiesChecksum\&quot;:\&quot;\&quot;,\&quot;MemorySectionName\&quot;:\&quot;None\&quot;,\&quot;MemorySectionChecksum\&quot;:\&quot;None\&quot;}&quot;,&quot;LocalParameters&quot;:&quot;{\&quot;Name\&quot;:\&quot;Default\&quot;,\&quot;Checksum\&quot;:\&quot;Default\&quot;,\&quot;PerInstancePropertiesChecksum\&quot;:\&quot;\&quot;,\&quot;MemorySectionName\&quot;:\&quot;None\&quot;,\&quot;MemorySectionChecksum\&quot;:\&quot;None\&quot;}&quot;,&quot;ParameterArguments&quot;:&quot;{\&quot;Name\&quot;:\&quot;Default\&quot;,\&quot;Checksum\&quot;:\&quot;Default\&quot;,\&quot;PerInstancePropertiesChecksum\&quot;:\&quot;\&quot;,\&quot;MemorySectionName\&quot;:\&quot;None\&quot;,\&quot;MemorySectionChecksum\&quot;:\&quot;None\&quot;}&quot;,&quot;SharedLocalDataStores&quot;:&quot;{\&quot;Name\&quot;:\&quot;Default\&quot;,\&quot;Checksum\&quot;:\&quot;Default\&quot;,\&quot;PerInstancePropertiesChecksum\&quot;:\&quot;\&quot;,\&quot;MemorySectionName\&quot;:\&quot;None\&quot;,\&quot;MemorySectionChecksum\&quot;:\&quot;None\&quot;}&quot;,&quot;GlobalDataStores&quot;:&quot;{\&quot;Name\&quot;:\&quot;Default\&quot;,\&quot;Checksum\&quot;:\&quot;Default\&quot;,\&quot;PerInstancePropertiesChecksum\&quot;:\&quot;\&quot;,\&quot;MemorySectionName\&quot;:\&quot;None\&quot;,\&quot;MemorySectionChecksum\&quot;:\&quot;None\&quot;}&quot;,&quot;InternalData&quot;:&quot;{\&quot;Name\&quot;:\&quot;Default\&quot;,\&quot;Checksum\&quot;:\&quot;Default\&quot;,\&quot;PerInstancePropertiesChecksum\&quot;:\&quot;\&quot;,\&quot;MemorySectionName\&quot;:\&quot;None\&quot;,\&quot;MemorySectionChecksum\&quot;:\&quot;None\&quot;}&quot;,&quot;Constants&quot;:&quot;{\&quot;Name\&quot;:\&quot;Default\&quot;,\&quot;Checksum\&quot;:\&quot;Default\&quot;,\&quot;PerInstancePropertiesChecksum\&quot;:\&quot;\&quot;,\&quot;MemorySectionName\&quot;:\&quot;None\&quot;,\&quot;MemorySectionChecksum\&quot;:\&quot;None\&quot;}&quot;,&quot;DataTransfers&quot;:&quot;{\&quot;Name\&quot;:\&quot;Default\&quot;,\&quot;Checksum\&quot;:\&quot;Default\&quot;,\&quot;PerInstancePropertiesChecksum\&quot;:\&quot;\&quot;,\&quot;MemorySectionName\&quot;:\&quot;None\&quot;,\&quot;MemorySectionChecksum\&quot;:\&quot;None\&quot;}&quot;,&quot;ModelData&quot;:&quot;{\&quot;Name\&quot;:\&quot;Default\&quot;,\&quot;Checksum\&quot;:\&quot;Default\&quot;,\&quot;PerInstancePropertiesChecksum\&quot;:\&quot;\&quot;,\&quot;MemorySectionName\&quot;:\&quot;None\&quot;,\&quot;MemorySectionChecksum\&quot;:\&quot;None\&quot;}&quot;,&quot;InitializeTerminate&quot;:&quot;{\&quot;Name\&quot;:\&quot;Default\&quot;,\&quot;Checksum\&quot;:\&quot;Default\&quot;,\&quot;PerInstancePropertiesChecksum\&quot;:\&quot;\&quot;,\&quot;MemorySectionName\&quot;:\&quot;None\&quot;,\&quot;MemorySectionChecksum\&quot;:\&quot;None\&quot;}&quot;,&quot;Execution&quot;:&quot;{\&quot;Name\&quot;:\&quot;Default\&quot;,\&quot;Checksum\&quot;:\&quot;Default\&quot;,\&quot;PerInstancePropertiesChecksum\&quot;:\&quot;\&quot;,\&quot;MemorySectionName\&quot;:\&quot;None\&quot;,\&quot;MemorySectionChecksum\&quot;:\&quot;None\&quot;}&quot;,&quot;SharedUtility&quot;:&quot;{\&quot;Name\&quot;:\&quot;Default\&quot;,\&quot;Checksum\&quot;:\&quot;Default\&quot;,\&quot;PerInstancePropertiesChecksum\&quot;:\&quot;\&quot;,\&quot;MemorySectionName\&quot;:\&quot;None\&quot;,\&quot;MemorySectionChecksum\&quot;:\&quot;None\&quot;}&quot;}</defaultsCMapping>
    <fundamentalSampleTimePeriod>0.0050000000000000001</fundamentalSampleTimePeriod>
    <globalVariables>sim_step</globalVariables>
    <hasBwsAccessed>true</hasBwsAccessed>
    <hasBwsAccessedByAnyModel>true</hasBwsAccessedByAnyModel>
    <inports type="ModelRefInfoRepo.InportInformation" uuid="35fbe2cb-ce80-4fda-aee8-5c8064ac5241">
      <isNotDerivPort>true</isNotDerivPort>
      <designMax>inf</designMax>
      <designMin>-inf</designMin>
      <indexType>2</indexType>
      <rateInfo type="ModelRefInfoRepo.RateInfo">
        <compiled>true</compiled>
        <nonFcnCallPartitionName>D1</nonFcnCallPartitionName>
        <period>0.0050000000000000001</period>
        <rateIdx>0</rateIdx>
      </rateInfo>
      <resolvedSignalObject></resolvedSignalObject>
      <sigNameToEMVCEMap type="ModelRefInfoRepo.SigNameEMVCEInfo" uuid="4353a610-9f74-4185-99b7-524809754055"/>
    </inports>
    <isInlineParamsOn>true</isInlineParamsOn>
    <isOrigInportVirtualBus>false</isOrigInportVirtualBus>
    <isOrigOutportVirtualBus>false</isOrigOutportVirtualBus>
    <isOrigOutportVirtualBus>false</isOrigOutportVirtualBus>
    <isOrigOutportVirtualBus>false</isOrigOutportVirtualBus>
    <isOrigOutportVirtualBus>false</isOrigOutportVirtualBus>
    <loggingSaveFormat>2</loggingSaveFormat>
    <maxFreqHz>-1</maxFreqHz>
    <origInportBusType></origInportBusType>
    <origInportElements></origInportElements>
    <origOutportBusType></origOutportBusType>
    <origOutportBusType></origOutportBusType>
    <origOutportBusType></origOutportBusType>
    <origOutportBusType></origOutportBusType>
    <origOutportElements></origOutportElements>
    <origOutportElements></origOutportElements>
    <origOutportElements></origOutportElements>
    <origOutportElements></origOutportElements>
    <outports type="ModelRefInfoRepo.OutportInformation" uuid="9c7b2495-e04d-46d5-bb6a-d76f9cb3a994">
      <designMax>inf</designMax>
      <designMin>-inf</designMin>
      <rateInfo type="ModelRefInfoRepo.RateInfo">
        <compiled>true</compiled>
        <nonFcnCallPartitionName>D1</nonFcnCallPartitionName>
        <period>0.0050000000000000001</period>
        <rateIdx>0</rateIdx>
      </rateInfo>
      <resolvedSignalObject></resolvedSignalObject>
      <sigNameToEMVCEMap type="ModelRefInfoRepo.SigNameEMVCEInfo" uuid="d1be51d1-0a34-4492-ab19-13dbc234b8e4"/>
    </outports>
    <outports type="ModelRefInfoRepo.OutportInformation" uuid="3f989671-2ef8-48cd-8d6f-a8c9e8b0d423">
      <designMax>inf</designMax>
      <designMin>-inf</designMin>
      <originalPortNumber>1</originalPortNumber>
      <rateInfo type="ModelRefInfoRepo.RateInfo">
        <compiled>true</compiled>
        <nonFcnCallPartitionName>D1</nonFcnCallPartitionName>
        <period>0.0050000000000000001</period>
        <rateIdx>0</rateIdx>
      </rateInfo>
      <resolvedSignalObject></resolvedSignalObject>
      <sigNameToEMVCEMap type="ModelRefInfoRepo.SigNameEMVCEInfo" uuid="b8e1d7ca-260b-42ce-b052-b300fb8e069f"/>
    </outports>
    <outports type="ModelRefInfoRepo.OutportInformation" uuid="22c2c68a-c029-4ec7-ac87-e4d69bc6a16e">
      <designMax>inf</designMax>
      <designMin>-inf</designMin>
      <originalPortNumber>2</originalPortNumber>
      <rateInfo type="ModelRefInfoRepo.RateInfo">
        <compiled>true</compiled>
        <nonFcnCallPartitionName>D1</nonFcnCallPartitionName>
        <period>0.0050000000000000001</period>
        <rateIdx>0</rateIdx>
      </rateInfo>
      <resolvedSignalObject></resolvedSignalObject>
      <sigNameToEMVCEMap type="ModelRefInfoRepo.SigNameEMVCEInfo" uuid="2071f304-8590-429e-b0dc-bd7673148030"/>
    </outports>
    <outports type="ModelRefInfoRepo.OutportInformation" uuid="0f1cc620-a49b-479e-8105-c6ae99008339">
      <designMax>inf</designMax>
      <designMin>-inf</designMin>
      <originalPortNumber>3</originalPortNumber>
      <rateInfo type="ModelRefInfoRepo.RateInfo">
        <compiled>true</compiled>
        <nonFcnCallPartitionName>D1</nonFcnCallPartitionName>
        <period>0.0050000000000000001</period>
        <rateIdx>0</rateIdx>
      </rateInfo>
      <resolvedSignalObject></resolvedSignalObject>
      <sigNameToEMVCEMap type="ModelRefInfoRepo.SigNameEMVCEInfo" uuid="ca23a261-42bd-4dc2-bbc2-902d48c798d9"/>
    </outports>
    <removeResetFunc>true</removeResetFunc>
    <runtimeNonFcnCallRateInfos type="ModelRefInfoRepo.RateInfo">
      <compiled>true</compiled>
      <nonFcnCallPartitionName>D1</nonFcnCallPartitionName>
      <period>0.0050000000000000001</period>
      <rateIdx>0</rateIdx>
    </runtimeNonFcnCallRateInfos>
    <sampleTimeInheritanceRule>2</sampleTimeInheritanceRule>
    <timingAndTaskingRegistry>&lt;?xml version=&quot;1.0&quot;?&gt;
&lt;MF0 version=&quot;1.1&quot; packageUris=&quot;http://schema.mathworks.com/mf0/slexec_mm_sto/R2018b&quot;&gt;
  &lt;sto.Registry type=&quot;sto.Registry&quot; uuid=&quot;71b87681-0f59-4d06-a896-83463c4b42ec&quot;&gt;
    &lt;clocks type=&quot;sto.Clock&quot; uuid=&quot;288853dd-7eec-4453-8f02-97abe953f677&quot;&gt;
      &lt;clockTickConstraint&gt;PeriodicWithFixedResolution&lt;/clockTickConstraint&gt;
      &lt;needsToProvideTimeDuringExecution&gt;true&lt;/needsToProvideTimeDuringExecution&gt;
      &lt;resolution&gt;0.0050000000000000001&lt;/resolution&gt;
      &lt;specifiedClockTickConstraint&gt;PeriodicWithFixedResolution&lt;/specifiedClockTickConstraint&gt;
      &lt;clockDomain type=&quot;sto.ClockDomain&quot; uuid=&quot;54fcb5f6-93ec-4b44-a335-1ef8bae7c310&quot;&gt;
        &lt;baseTaskID&gt;_task0&lt;/baseTaskID&gt;
        &lt;computedFundamentalStepSize&gt;0.0050000000000000001&lt;/computedFundamentalStepSize&gt;
        &lt;rates type=&quot;sto.Rate&quot; uuid=&quot;758004af-4a9a-4ffa-a3a9-54b11a16cbc6&quot;/&gt;
        &lt;rates type=&quot;sto.Rate&quot; uuid=&quot;b4ca21a4-dfca-45de-92d8-ed6a4876aaef&quot;/&gt;
        &lt;rootTaskHierarchyElements type=&quot;sto.Task&quot; uuid=&quot;a5ad7df1-2a05-4d65-95b9-f50a7b4f2d92&quot;&gt;
          &lt;isExecutable&gt;true&lt;/isExecutable&gt;
          &lt;orderIndex&gt;1&lt;/orderIndex&gt;
          &lt;rates type=&quot;sto.Rate&quot; uuid=&quot;758004af-4a9a-4ffa-a3a9-54b11a16cbc6&quot;&gt;
            &lt;annotation&gt;FiM&lt;/annotation&gt;
            &lt;colorIndex&gt;8&lt;/colorIndex&gt;
            &lt;description&gt;Fixed in Minor Step&lt;/description&gt;
            &lt;eventSourceType&gt;UNSPECIFIED_EVENT_SOURCE&lt;/eventSourceType&gt;
            &lt;rateIDX&gt;-1&lt;/rateIDX&gt;
            &lt;registry type=&quot;sto.Registry&quot; uuid=&quot;71b87681-0f59-4d06-a896-83463c4b42ec&quot;/&gt;
            &lt;taskId&gt;_task0&lt;/taskId&gt;
            &lt;useForExecution&gt;NotForExecution&lt;/useForExecution&gt;
            &lt;rateSpec type=&quot;sto.RateSpec&quot; uuid=&quot;3f9c44ec-f76b-410f-901d-d42fb1d591fd&quot;&gt;
              &lt;offset&gt;1&lt;/offset&gt;
              &lt;rateType&gt;ZOHContinuous&lt;/rateType&gt;
            &lt;/rateSpec&gt;
          &lt;/rates&gt;
          &lt;rates type=&quot;sto.Rate&quot; uuid=&quot;b4ca21a4-dfca-45de-92d8-ed6a4876aaef&quot;&gt;
            &lt;annotation&gt;D1&lt;/annotation&gt;
            &lt;colorIndex&gt;2&lt;/colorIndex&gt;
            &lt;description&gt;Discrete 1&lt;/description&gt;
            &lt;eventSourceType&gt;UNSPECIFIED_EVENT_SOURCE&lt;/eventSourceType&gt;
            &lt;registry type=&quot;sto.Registry&quot; uuid=&quot;71b87681-0f59-4d06-a896-83463c4b42ec&quot;/&gt;
            &lt;taskId&gt;_task0&lt;/taskId&gt;
            &lt;rateSpec type=&quot;sto.RateSpec&quot; uuid=&quot;f4e997d7-670b-4abd-a3af-a9f1ca8795f3&quot;&gt;
              &lt;period&gt;0.0050000000000000001&lt;/period&gt;
              &lt;rateType&gt;ClassicPeriodicDiscrete&lt;/rateType&gt;
            &lt;/rateSpec&gt;
          &lt;/rates&gt;
          &lt;elementType&gt;Task&lt;/elementType&gt;
          &lt;identifier&gt;_task0&lt;/identifier&gt;
          &lt;priority&gt;40&lt;/priority&gt;
        &lt;/rootTaskHierarchyElements&gt;
      &lt;/clockDomain&gt;
    &lt;/clocks&gt;
    &lt;executionSpec&gt;Undetermined&lt;/executionSpec&gt;
    &lt;taskDependencyGraph type=&quot;sto.SerializedTaskConnectionList&quot; uuid=&quot;cccc6336-a662-4311-b370-683c6f2e16a9&quot;&gt;
      &lt;taskIdentifier&gt;_task0&lt;/taskIdentifier&gt;
    &lt;/taskDependencyGraph&gt;
    &lt;taskPriorityDirection&gt;HighNumberLast&lt;/taskPriorityDirection&gt;
    &lt;tasks type=&quot;sto.Task&quot; uuid=&quot;a5ad7df1-2a05-4d65-95b9-f50a7b4f2d92&quot;/&gt;
  &lt;/sto.Registry&gt;
&lt;/MF0&gt;</timingAndTaskingRegistry>
    <zeroInternalMemoryAtStartupUnchecked>true</zeroInternalMemoryAtStartupUnchecked>
    <FMUBlockMap type="ModelRefInfoRepo.FMUBlockInfo" uuid="51c603aa-ca2b-4ae5-8df9-3d450856e755"/>
    <codeGenInfo type="ModelRefInfoRepo.CodeGenInformation" uuid="41c041e0-30bc-4837-98bb-d39d12ee48c5"/>
    <configSettingsForConsistencyChecks type="ModelRefInfoRepo.ConfigSettingsForConsistencyChecks" uuid="47767171-a2ec-4c1c-86bb-0123b09245cf">
      <consistentOutportInitialization>true</consistentOutportInitialization>
      <fixedStepSize>0.0050000000000000001</fixedStepSize>
      <hasHybridSampleTime>true</hasHybridSampleTime>
      <optimizedInitCode>true</optimizedInitCode>
      <signalLoggingSaveFormat>2</signalLoggingSaveFormat>
      <solverName>FixedStepDiscrete</solverName>
      <solverType>SOLVER_TYPE_FIXEDSTEP</solverType>
      <useDivForNetSlopComp>2</useDivForNetSlopComp>
      <hardwareSettings type="ModelRefInfoRepo.HardwareSettings" uuid="fdd01205-36c7-48a1-8587-94fe9b63d8f7">
        <prodBitPerChar>8</prodBitPerChar>
        <prodBitPerDouble>64</prodBitPerDouble>
        <prodBitPerFloat>32</prodBitPerFloat>
        <prodBitPerInt>32</prodBitPerInt>
        <prodBitPerLong>32</prodBitPerLong>
        <prodBitPerLongLong>64</prodBitPerLongLong>
        <prodBitPerPointer>32</prodBitPerPointer>
        <prodBitPerPtrDiffT>32</prodBitPerPtrDiffT>
        <prodBitPerShort>16</prodBitPerShort>
        <prodBitPerSizeT>32</prodBitPerSizeT>
        <prodEndianess>1</prodEndianess>
        <prodLargestAtomicInteger>2</prodLargestAtomicInteger>
        <prodLongLongMode>true</prodLongLongMode>
        <prodShiftRight>true</prodShiftRight>
        <prodWordSize>32</prodWordSize>
      </hardwareSettings>
    </configSettingsForConsistencyChecks>
    <dataPortGroup type="ModelRefInfoRepo.DataPortGroup" uuid="4632bf4b-e915-4f77-96d4-e52b6c2fe1aa">
      <dataInputPorts>0</dataInputPorts>
      <dataOutputPorts>0</dataOutputPorts>
      <dataOutputPorts>1</dataOutputPorts>
      <dataOutputPorts>2</dataOutputPorts>
      <dataOutputPorts>3</dataOutputPorts>
    </dataPortGroup>
    <interfaceParameterInfo type="ModelRefInfoRepo.InterfaceParameterInfo" uuid="a6aeb8ed-bdc4-47b6-bd22-26a2198833e6"/>
    <methodInfo type="ModelRefInfoRepo.MethodExistenceInfo" uuid="496342cb-8fed-4726-b065-b4f805d0d141">
      <hasSystemInitializeMethod>true</hasSystemInitializeMethod>
      <hasTerminateMethod>true</hasTerminateMethod>
    </methodInfo>
    <periodicEventPortUnsupportedBlockInfo type="ModelRefInfoRepo.PeriodicEventPortUnsupportedBlockInfo" uuid="b4bca90a-2181-4fa2-93a0-558c046b63c1"/>
    <portGroupsRequireSameRate type="ModelRefInfoRepo.PortGroupsRequireSameRate" uuid="e3903684-f411-4221-8582-82ec51f5a0bb">
      <DSMPortGroups type="ModelRefInfoRepo.NameToPortGroupIdxVectMap" uuid="f02daa67-8bae-4d45-8017-df54eabb6db2"/>
      <GlobalDSMPortGroups type="ModelRefInfoRepo.NameToPortGroupIdxVectMap" uuid="79ac3c49-631f-448d-b59e-009c407a56e3"/>
      <mergedPortGroups type="ModelRefInfoRepo.NameToPortGroupIdxVectMap" uuid="53fb2a33-a532-49c0-92ef-5fbf6e5feddd"/>
    </portGroupsRequireSameRate>
    <rateSpecOfGlobalDSMAccessedByDescExpFcnMdlMap type="ModelRefInfoRepo.GlobalDSMRateSpecMap" uuid="5b9c53e4-9ac0-4fd9-a48a-60ab5b7260d1"/>
    <simulinkFunctions type="ModelRefInfoRepo.SimulinkFunctions" uuid="8f6f34dc-0e7d-4079-899a-6f470c05e6a7">
      <compServicePortMap>AAFJTQAAAAAOAAAAMAAAAAYAAAAIAAAABgAAAAAAAAAFAAAACAAAAAAAAAAAAAAAAQAAAAAAAAAJAAAAAAAAAA==</compServicePortMap>
      <compSimulinkFunctionCatalog></compSimulinkFunctionCatalog>
      <variantSimulinkFunctions type="ModelRefInfoRepo.VariantSimulinkFunctions" uuid="4fb31f7d-59db-459d-899d-6daa2be4b3e7"/>
    </simulinkFunctions>
    <stateWriterToOwnerMap type="ModelRefInfoRepo.StateWriterInfo" uuid="6c41fb08-97d1-4c68-adfe-a3c267890bae"/>
  </ModelRefInfoRepo.ModelRefInfoRoot>
</MF0>